katsuba-0.2.2.dist-info/METADATA
katsuba-0.2.2.dist-info/WHEEL
katsuba/op.pyi
katsuba/py.typed
katsuba/utils.pyi
katsuba/wad.pyi
katsuba/__init__.py
katsuba/__init__.pyi
katsuba/katsuba.pyd
katsuba-0.2.2.dist-info/RECORD
