Metadata-Version: 2.4
Name: katsuba
Version: 0.2.2
Classifier: Intended Audience :: Developers
Classifier: License :: OSI Approved :: ISC License (ISCL)
Classifier: Programming Language :: Rust
Classifier: Programming Language :: Python :: 3.10
Classifier: Programming Language :: Python :: 3.11
Classifier: Programming Language :: Python :: 3.12
Classifier: Operating System :: MacOS
Classifier: Operating System :: Microsoft :: Windows
Classifier: Operating System :: POSIX :: Linux
Summary: Python bindings to the katsuba Rust libraries
Author: Valentin B. <valentin.be@protonmail.com>
Author-email: Valentin B. <valentin.be@protonmail.com>
License: ISC
